expdata_libsvm/__init__.py
expdata_libsvm/example.py
expdata_libsvm/read_data.py
expdata_libsvm/exp_data/Duke/test_data.bz2
expdata_libsvm/exp_data/Duke/training_data.bz2
expdata_libsvm/exp_data/Ijcnn/test_data.bz2
expdata_libsvm/exp_data/Ijcnn/training_data.bz2
expdata_libsvm/exp_data/Letter/test_data.txt
expdata_libsvm/exp_data/Letter/training_data.txt
expdata_libsvm/exp_data/Shuttle/test_data.txt
expdata_libsvm/exp_data/Shuttle/training_data.txt
expdata_libsvm/exp_data/Vowel/test_data.txt
expdata_libsvm/exp_data/Vowel/training_data.txt
expdata_libsvm/exp_data/w8a/test_data.txt
expdata_libsvm/exp_data/w8a/training_data.txt
expdata_libsvm-0.1.8.dist-info/METADATA
expdata_libsvm-0.1.8.dist-info/WHEEL
expdata_libsvm-0.1.8.dist-info/RECORD
