Metadata-Version: 2.4
Name: expdata_libsvm
Version: 0.1.8
Summary: datasets
Author-email: Junshan Yin <junshanyin@163.com>
Requires-Dist: numpy==2.2.6
Requires-Dist: scikit-learn==1.7.1
